critical/__init__.py
critical/admin.py
critical/api.py
critical/apps.py
critical/exceptions.py
critical/models.py
critical/services.py
critical/tasks.py
critical/utils.py
critical/management/__init__.py
critical/management/commands/__init__.py
critical/management/commands/empty_critical_css.py
critical/migrations/0001_initial.py
critical/migrations/__init__.py
critical/signals/__init__.py
critical/signals/handlers.py
critical/templatetags/__init__.py
critical/templatetags/critical_tags.py
django_critical_css-0.0.1.dist-info/LICENSE.rst
django_critical_css-0.0.1.dist-info/METADATA
django_critical_css-0.0.1.dist-info/WHEEL
django_critical_css-0.0.1.dist-info/top_level.txt
django_critical_css-0.0.1.dist-info/RECORD
