Metadata-Version: 2.1
Name: django-critical-css
Version: 0.0.1
Summary: django-critical-css aims to speed up webpage rendering by saving critical css in db.
Home-page: https://github.com/lenarother/django-critical-css
Author: Magdalena Rother
Author-email: rother.magdalena@gmail.com
License: UNKNOWN
Project-URL: Bug Reports, https://github.com/lenarother/django-critical-css/issues
Project-URL: Source, https://github.com/lenarother/django-critical-css
Keywords: django
Platform: UNKNOWN
Classifier: Environment :: Web Environment
Classifier: Framework :: Django
Classifier: Intended Audience :: Developers
Classifier: License :: OSI Approved :: MIT License
Classifier: Programming Language :: Python :: 3
Classifier: Programming Language :: Python :: 3.6
Requires-Dist: django-rq
Requires-Dist: django-inline-static
